{
  "$schema": "https://hypersync.io/schemas/mechanism_profile.schema.json",
  "created": "2025-11-18T09:31:52.944787",
  "description": "Resource profiles for all consensus mechanisms",
  "profiles": {
    "byzantine_fault_tolerant": {
      "category": "byzantine_fault_tolerant",
      "characteristics": {
        "complexity": "very_high",
        "consistency": "strong",
        "fault_tolerance": "byzantine (f < n/3)",
        "partition_tolerance": "moderate"
      },
      "id": "byzantine_fault_tolerant",
      "name": "Byzantine Fault Tolerant (BFT)",
      "resources": {
        "cpu_cores_min": 8,
        "cpu_cores_recommended": 16,
        "disk_io_ops": "very_high",
        "gpu_required": false,
        "memory_mb_min": 2048,
        "memory_mb_recommended": 4096,
        "network_bandwidth_mbps": 500
      },
      "scalability": {
        "latency_ms_typical": "200-500",
        "max_nodes_tested": 100,
        "throughput_ops_sec": "1000-5000"
      },
      "weight": "heavy"
    },
    "crdt": {
      "category": "conflict_free",
      "characteristics": {
        "complexity": "moderate",
        "consistency": "eventual",
        "fault_tolerance": "excellent",
        "partition_tolerance": "excellent"
      },
      "id": "crdt",
      "name": "CRDT",
      "resources": {
        "cpu_cores_min": 1,
        "cpu_cores_recommended": 2,
        "disk_io_ops": "low",
        "gpu_required": false,
        "memory_mb_min": 128,
        "memory_mb_recommended": 256,
        "network_bandwidth_mbps": 20
      },
      "scalability": {
        "latency_ms_typical": "10-50",
        "max_nodes_tested": 1000,
        "throughput_ops_sec": "5000-10000"
      },
      "weight": "lightweight"
    },
    "geometric_consensus": {
      "category": "geometric",
      "characteristics": {
        "complexity": "extreme",
        "consistency": "strong",
        "fault_tolerance": "byzantine (geometric)",
        "geometric_consensus": true,
        "manifold_operations": true,
        "partition_tolerance": "excellent"
      },
      "id": "geometric_consensus",
      "name": "Geometric Consensus",
      "resources": {
        "cpu_cores_min": 16,
        "cpu_cores_recommended": 32,
        "disk_io_ops": "extreme",
        "gpu_memory_mb": 8192,
        "gpu_required": true,
        "memory_mb_min": 4096,
        "memory_mb_recommended": 8192,
        "network_bandwidth_mbps": 1000
      },
      "scalability": {
        "latency_ms_typical": "2000-10000",
        "max_nodes_tested": 100,
        "throughput_ops_sec": "50-500"
      },
      "weight": "very_heavy"
    },
    "gossip_protocol": {
      "category": "epidemic",
      "characteristics": {
        "complexity": "low",
        "consistency": "eventual",
        "fault_tolerance": "high",
        "partition_tolerance": "excellent"
      },
      "id": "gossip_protocol",
      "name": "Gossip Protocol",
      "resources": {
        "cpu_cores_min": 1,
        "cpu_cores_recommended": 2,
        "disk_io_ops": "low",
        "gpu_required": false,
        "memory_mb_min": 64,
        "memory_mb_recommended": 128,
        "network_bandwidth_mbps": 10
      },
      "scalability": {
        "latency_ms_typical": "50-200",
        "max_nodes_tested": 1000,
        "throughput_ops_sec": "1000-5000"
      },
      "weight": "lightweight"
    },
    "hotstuff": {
      "category": "byzantine_fault_tolerant",
      "characteristics": {
        "complexity": "very_high",
        "consistency": "strong",
        "fault_tolerance": "byzantine (f < n/3)",
        "optimized_for": "large_networks",
        "partition_tolerance": "good"
      },
      "id": "hotstuff",
      "name": "HotStuff",
      "resources": {
        "cpu_cores_min": 8,
        "cpu_cores_recommended": 16,
        "disk_io_ops": "very_high",
        "gpu_required": false,
        "memory_mb_min": 2048,
        "memory_mb_recommended": 4096,
        "network_bandwidth_mbps": 500
      },
      "scalability": {
        "latency_ms_typical": "500-2000",
        "max_nodes_tested": 500,
        "throughput_ops_sec": "5000-20000"
      },
      "weight": "heavy"
    },
    "merkle_tree": {
      "category": "integrity_verification",
      "characteristics": {
        "complexity": "low",
        "consistency": "strong",
        "fault_tolerance": "high",
        "partition_tolerance": "good"
      },
      "id": "merkle_tree",
      "name": "Merkle Tree",
      "resources": {
        "cpu_cores_min": 1,
        "cpu_cores_recommended": 2,
        "disk_io_ops": "moderate",
        "gpu_required": false,
        "memory_mb_min": 64,
        "memory_mb_recommended": 128,
        "network_bandwidth_mbps": 10
      },
      "scalability": {
        "latency_ms_typical": "5-20",
        "max_nodes_tested": 10000,
        "throughput_ops_sec": "10000+"
      },
      "weight": "lightweight"
    },
    "paxos": {
      "category": "consensus",
      "characteristics": {
        "complexity": "high",
        "consistency": "strong",
        "fault_tolerance": "crash (f < n/2)",
        "partition_tolerance": "good"
      },
      "id": "paxos",
      "name": "Paxos",
      "resources": {
        "cpu_cores_min": 4,
        "cpu_cores_recommended": 8,
        "disk_io_ops": "high",
        "gpu_required": false,
        "memory_mb_min": 512,
        "memory_mb_recommended": 1024,
        "network_bandwidth_mbps": 100
      },
      "scalability": {
        "latency_ms_typical": "100-300",
        "max_nodes_tested": 500,
        "throughput_ops_sec": "3000-10000"
      },
      "weight": "moderate"
    },
    "proof_of_stake": {
      "category": "blockchain",
      "characteristics": {
        "complexity": "high",
        "consistency": "eventual",
        "energy_efficient": true,
        "fault_tolerance": "byzantine (f < n/3)",
        "partition_tolerance": "excellent"
      },
      "id": "proof_of_stake",
      "name": "Proof of Stake",
      "resources": {
        "cpu_cores_min": 4,
        "cpu_cores_recommended": 8,
        "disk_io_ops": "high",
        "gpu_required": false,
        "memory_mb_min": 1024,
        "memory_mb_recommended": 2048,
        "network_bandwidth_mbps": 100
      },
      "scalability": {
        "latency_ms_typical": "1000-5000",
        "max_nodes_tested": 10000,
        "throughput_ops_sec": "1000-5000"
      },
      "weight": "moderate"
    },
    "quorum_based": {
      "category": "voting",
      "characteristics": {
        "complexity": "low",
        "consistency": "strong",
        "fault_tolerance": "moderate (majority)",
        "partition_tolerance": "moderate"
      },
      "id": "quorum_based",
      "name": "Quorum-based",
      "resources": {
        "cpu_cores_min": 2,
        "cpu_cores_recommended": 4,
        "disk_io_ops": "moderate",
        "gpu_required": false,
        "memory_mb_min": 128,
        "memory_mb_recommended": 256,
        "network_bandwidth_mbps": 30
      },
      "scalability": {
        "latency_ms_typical": "50-150",
        "max_nodes_tested": 500,
        "throughput_ops_sec": "2000-5000"
      },
      "weight": "light"
    },
    "raft": {
      "category": "leader_election",
      "characteristics": {
        "complexity": "moderate",
        "consistency": "strong",
        "fault_tolerance": "crash (f < n/2)",
        "partition_tolerance": "moderate"
      },
      "id": "raft",
      "name": "Raft",
      "resources": {
        "cpu_cores_min": 2,
        "cpu_cores_recommended": 4,
        "disk_io_ops": "high",
        "gpu_required": false,
        "memory_mb_min": 512,
        "memory_mb_recommended": 1024,
        "network_bandwidth_mbps": 100
      },
      "scalability": {
        "latency_ms_typical": "50-200",
        "max_nodes_tested": 1000,
        "throughput_ops_sec": "5000-15000"
      },
      "weight": "moderate"
    },
    "riemannian_barycenter": {
      "category": "geometric",
      "characteristics": {
        "complexity": "extreme",
        "consistency": "strong",
        "fault_tolerance": "byzantine (geometric)",
        "geometric_consensus": true,
        "partition_tolerance": "excellent"
      },
      "id": "riemannian_barycenter",
      "name": "Riemannian Barycenter",
      "resources": {
        "cpu_cores_min": 16,
        "cpu_cores_recommended": 32,
        "disk_io_ops": "extreme",
        "gpu_memory_mb": 8192,
        "gpu_required": true,
        "memory_mb_min": 4096,
        "memory_mb_recommended": 8192,
        "network_bandwidth_mbps": 1000
      },
      "scalability": {
        "latency_ms_typical": "1000-5000",
        "max_nodes_tested": 100,
        "throughput_ops_sec": "100-1000"
      },
      "weight": "very_heavy"
    },
    "simple_bft": {
      "category": "byzantine_fault_tolerant",
      "characteristics": {
        "complexity": "moderate",
        "consistency": "strong",
        "fault_tolerance": "byzantine (f < n/3)",
        "partition_tolerance": "moderate",
        "safety_critical": true
      },
      "id": "simple_bft",
      "name": "Simple BFT",
      "resources": {
        "cpu_cores_min": 2,
        "cpu_cores_recommended": 4,
        "disk_io_ops": "moderate",
        "gpu_required": false,
        "memory_mb_min": 256,
        "memory_mb_recommended": 512,
        "network_bandwidth_mbps": 50
      },
      "scalability": {
        "latency_ms_typical": "100-300",
        "max_nodes_tested": 100,
        "throughput_ops_sec": "500-2000"
      },
      "weight": "light"
    },
    "tendermint": {
      "category": "byzantine_fault_tolerant",
      "characteristics": {
        "complexity": "very_high",
        "consistency": "strong",
        "fault_tolerance": "byzantine (f < n/3)",
        "finality": "instant",
        "partition_tolerance": "good"
      },
      "id": "tendermint",
      "name": "Tendermint",
      "resources": {
        "cpu_cores_min": 8,
        "cpu_cores_recommended": 16,
        "disk_io_ops": "very_high",
        "gpu_required": false,
        "memory_mb_min": 2048,
        "memory_mb_recommended": 4096,
        "network_bandwidth_mbps": 500
      },
      "scalability": {
        "latency_ms_typical": "1000-3000",
        "max_nodes_tested": 200,
        "throughput_ops_sec": "1000-10000"
      },
      "weight": "heavy"
    },
    "vector_clock": {
      "category": "causality_tracking",
      "characteristics": {
        "complexity": "low",
        "consistency": "causal",
        "fault_tolerance": "moderate",
        "partition_tolerance": "good"
      },
      "id": "vector_clock",
      "name": "Vector Clock",
      "resources": {
        "cpu_cores_min": 1,
        "cpu_cores_recommended": 1,
        "disk_io_ops": "minimal",
        "gpu_required": false,
        "memory_mb_min": 32,
        "memory_mb_recommended": 64,
        "network_bandwidth_mbps": 5
      },
      "scalability": {
        "latency_ms_typical": "1-10",
        "max_nodes_tested": 500,
        "throughput_ops_sec": "10000+"
      },
      "weight": "lightweight"
    }
  }
}